CHANGELOG
LICENSE
MANIFEST.in
README.rst
setup.py
django_rt/__init__.py
django_rt/event.py
django_rt/publish.py
django_rt/resource.py
django_rt/runcourier.py
django_rt/settings.py
django_rt/sse.py
django_rt/utils.py
django_rt/views.py
django_rt.egg-info/PKG-INFO
django_rt.egg-info/SOURCES.txt
django_rt.egg-info/dependency_links.txt
django_rt.egg-info/entry_points.txt
django_rt.egg-info/not-zip-safe
django_rt.egg-info/requires.txt
django_rt.egg-info/top_level.txt
django_rt/bin/djangort-courier.py
django_rt/couriers/__init__.py
django_rt/couriers/asyncio_courier.py
django_rt/couriers/courier.py
django_rt/couriers/gevent_courier.py